pypptkit/__init__.py
pypptkit/configs.py
pypptkit/main.py
pypptkit/static.py
pypptkit/utils.py
pypptkit-0.0.5.dist-info/LICENSE
pypptkit-0.0.5.dist-info/METADATA
pypptkit-0.0.5.dist-info/WHEEL
pypptkit-0.0.5.dist-info/entry_points.txt
pypptkit-0.0.5.dist-info/top_level.txt
pypptkit-0.0.5.dist-info/RECORD
