Metadata-Version: 2.1
Name: pypptkit
Version: 0.0.5
Summary: pypptkit helps doing things with ppt files
Home-page: https://veltzer.github.io/pypptkit
Download-URL: https://github.com/veltzer/pypptkit
Author: Mark Veltzer
Author-email: mark.veltzer@gmail.com
Maintainer: Mark Veltzer
Maintainer-email: mark.veltzer@gmail.com
License: MIT
Keywords: ppt,download,convert-to-text
Platform: python3
Classifier: Development Status :: 4 - Beta
Classifier: Environment :: Console
Classifier: Operating System :: OS Independent
Classifier: Programming Language :: Python
Classifier: Programming Language :: Python :: 3
Classifier: Programming Language :: Python :: 3 :: Only
Classifier: Programming Language :: Python :: 3.11
Classifier: Topic :: Utilities
Classifier: License :: OSI Approved :: MIT License
License-File: LICENSE
Requires-Dist: pytconf
Requires-Dist: pylogconf
Requires-Dist: python-pptx
Requires-Dist: pyvardump
